fluidsymbolic/__init__.py
fluidsymbolic/stream.py
fluidsymbolic/sympyfication.py
fluidsymbolic-0.0.1.dist-info/METADATA
fluidsymbolic-0.0.1.dist-info/WHEEL
fluidsymbolic-0.0.1.dist-info/top_level.txt
fluidsymbolic-0.0.1.dist-info/RECORD
